<?xml version="1.0" encoding="UTF-8"?>
<!DOCTYPE mapper PUBLIC "-//mybatis.org//DTD Mapper 3.0//EN" "http://mybatis.org/dtd/mybatis-3-mapper.dtd">

<mapper namespace="kosmo.team.project.dao.StadiumDAO">

	<select id="getStadiumList"
		resultType="kosmo.team.project.dto.StadiumDTO" parameterType="kosmo.team.project.dto.StadiumDTO">
		select * from (
		select rownum RNUM, zxcvb.* from (
		select
		st.stadium_no AS "stadium_no"
		,st.stadium_name AS "stadium_name"
		,s.name
		AS
		"sido_name"
		,si.name as "sigungu_name"
		,st.detailed_address as
		"detail_address"
		,to_char(st.reg_date, 'YYYY-MM-DD') AS "reg_date"
		,st.content as "content"
		,st.stadium_status as "stadium_status"

		FROM
		stadium st
		LEFT
		JOIN sido s ON st.sido_name = s.sido_id
		LEFT JOIN sigungu
		si ON
		st.sigungu_name = si.sigungu_id

        <![CDATA[ ) zxcvb) where RNUM >= #{begin_rowNo} and RNUM <= #{end_rowNo} ]]>
	</select>

	<select id="getStadiumListCnt" resultType="int">
		select
		count(*)
		from
		stadium
	</select>	
	
	
	<select id="getStadiumListAllCnt" resultType="int">
		select
		count(*)
		FROM
		stadium st
		LEFT JOIN sido s ON st.sido_name =
		s.sido_id
		LEFT JOIN
		sigungu si ON st.sigungu_name = si.sigungu_id



	</select>
	
	
	
	<select id="getStadium" parameterType="int"
		resultType="kosmo.team.project.dto.StadiumDTO">

		select
		st.stadium_no AS "stadium_no"
		,st.stadium_name AS "stadium_name"
		,s.name AS "sido_name"
		,si.name as "sigungu_name"
		,st.detailed_address
		as
		"detail_address"
		,to_char(st.reg_date, 'YYYY-MM-DD') AS "reg_date"
		,st.content as "content"
		,st.stadium_status as "stadium_status"

		FROM
		stadium st
		LEFT JOIN sido s ON st.sido_name =
		s.sido_id
		LEFT JOIN
		sigungu
		si ON st.sigungu_name = si.sigungu_id

		where
		stadium_no=#{stadium_no}
	</select>
	
	
	
	
	
	
</mapper>